pyswat/__init__.py
pyswat/pyswat_generate_template_configuration_json_file.py
pyswat/pyswat_read_model_configuration_file.py
pyswat/auxiliary/__init__.py
pyswat/auxiliary/line_count.py
pyswat/auxiliary/text_reader_string.py
pyswat/classes/__init__.py
pyswat/classes/hru.py
pyswat/classes/pycase.py
pyswat/classes/subbasin.py
pyswat/classes/swatpara.py
pyswat/classes/watershed.py
swaty/__init__.py
swaty/pyswat_generate_template_configuration_json_file.py
swaty/pyswat_read_model_configuration_file.py
swaty/swaty_generate_template_configuration_json_file.py
swaty/swaty_read_model_configuration_file.py
swaty/auxiliary/__init__.py
swaty/auxiliary/line_count.py
swaty/auxiliary/text_reader_string.py
swaty/classes/__init__.py
swaty/classes/hru.py
swaty/classes/pycase.py
swaty/classes/subbasin.py
swaty/classes/swatpara.py
swaty/classes/watershed.py
tests/__init__.py
tests/test_pyswat.py
swaty-0.1.6.dist-info/AUTHORS.rst
swaty-0.1.6.dist-info/LICENSE
swaty-0.1.6.dist-info/LICENSE.md
swaty-0.1.6.dist-info/METADATA
swaty-0.1.6.dist-info/WHEEL
swaty-0.1.6.dist-info/top_level.txt
swaty-0.1.6.dist-info/RECORD
